easynmpython/__init__.py
easynmpython/networking/__init__.py
easynmpython/networking/apflag.py
easynmpython/networking/apmode.py
easynmpython/networking/apsecurityflag.py
easynmpython/networking/byteflagenum.py
easynmpython/networking/client.py
easynmpython/networking/devicetype.py
easynmpython/networking/wificapability.py
easynmpython/networking/wirelessclient.py
easynmpython-1.0.14.dist-info/METADATA
easynmpython-1.0.14.dist-info/WHEEL
easynmpython-1.0.14.dist-info/top_level.txt
easynmpython-1.0.14.dist-info/RECORD
